{
  "businesses":[
     {
        "id":"xEnNFXtMLDF5kZDxfaCJgA",
        "alias":"the-halal-guys-new-york-2",
        "name":"The Halal Guys",
        "image_url":"https://s3-media2.fl.yelpcdn.com/bphoto/i6QRVRliZ42stZUp7795jQ/o.jpg",
        "is_closed":false,
        "url":"https://www.yelp.com/biz/the-halal-guys-new-york-2?adjust_creative=sBCogxx-5i49wpeuzo-8mQ&utm_campaign=yelp_api_v3&utm_medium=api_v3_business_search&utm_source=sBCogxx-5i49wpeuzo-8mQ",
        "review_count":8923,
        "categories":[
           {
              "alias":"foodstands",
              "title":"Food Stands"
           },
           {
              "alias":"mideastern",
              "title":"Middle Eastern"
           },
           {
              "alias":"halal",
              "title":"Halal"
           }
        ],
        "rating":4,
        "coordinates":{
           "latitude":40.7617559582706,
           "longitude":-73.979229927063
        },
        "transactions":[

        ],
        "price":"$",
        "location":{
           "address1":"W 53rd St 6th Ave",
           "address2":null,
           "address3":"",
           "city":"New York",
           "zip_code":"10019",
           "country":"US",
           "state":"NY",
           "display_address":[
              "W 53rd St 6th Ave",
              "New York, NY 10019"
           ]
        },
        "phone":"",
        "display_phone":"",
        "distance":6388.839589432905
     },
     {
        "id":"44SY464xDHbvOcjDzRbKkQ",
        "alias":"ippudo-new-york-new-york",
        "name":"Ippudo New York",
        "image_url":"https://s3-media3.fl.yelpcdn.com/bphoto/vD-5ypZnkzaqiF3mlurg2Q/o.jpg",
        "is_closed":false,
        "url":"https://www.yelp.com/biz/ippudo-new-york-new-york?adjust_creative=sBCogxx-5i49wpeuzo-8mQ&utm_campaign=yelp_api_v3&utm_medium=api_v3_business_search&utm_source=sBCogxx-5i49wpeuzo-8mQ",
        "review_count":9430,
        "categories":[
           {
              "alias":"ramen",
              "title":"Ramen"
           }
        ],
        "rating":4,
        "coordinates":{
           "latitude":40.73092,
           "longitude":-73.99015
        },
        "transactions":[

        ],
        "price":"$$",
        "location":{
           "address1":"65 4th Ave",
           "address2":"",
           "address3":"",
           "city":"New York",
           "zip_code":"10003",
           "country":"US",
           "state":"NY",
           "display_address":[
              "65 4th Ave",
              "New York, NY 10003"
           ]
        },
        "phone":"+12123880088",
        "display_phone":"(212) 388-0088",
        "distance":2855.84485141638
     },
     {
        "id":"V7lXZKBDzScDeGB8JmnzSA",
        "alias":"katzs-delicatessen-new-york",
        "name":"Katz's Delicatessen",
        "image_url":"https://s3-media4.fl.yelpcdn.com/bphoto/qr7eSU6CFwRGZ7Rc-QEoTQ/o.jpg",
        "is_closed":false,
        "url":"https://www.yelp.com/biz/katzs-delicatessen-new-york?adjust_creative=sBCogxx-5i49wpeuzo-8mQ&utm_campaign=yelp_api_v3&utm_medium=api_v3_business_search&utm_source=sBCogxx-5i49wpeuzo-8mQ",
        "review_count":9500,
        "categories":[
           {
              "alias":"delis",
              "title":"Delis"
           },
           {
              "alias":"sandwiches",
              "title":"Sandwiches"
           }
        ],
        "rating":4,
        "coordinates":{
           "latitude":40.72222,
           "longitude":-73.98751
        },
        "transactions":[
           "delivery",
           "pickup"
        ],
        "price":"$$",
        "location":{
           "address1":"205 E Houston St",
           "address2":"",
           "address3":"",
           "city":"New York",
           "zip_code":"10002",
           "country":"US",
           "state":"NY",
           "display_address":[
              "205 E Houston St",
              "New York, NY 10002"
           ]
        },
        "phone":"+12122542246",
        "display_phone":"(212) 254-2246",
        "distance":1947.3740045141433
     },
     {
        "id":"xOw4aafJRji9XomGunlvcQ",
        "alias":"central-park-new-york",
        "name":"Central Park",
        "image_url":"https://s3-media2.fl.yelpcdn.com/bphoto/oQQIa-DExchCgEyOHsrHCw/o.jpg",
        "is_closed":false,
        "url":"https://www.yelp.com/biz/central-park-new-york?adjust_creative=sBCogxx-5i49wpeuzo-8mQ&utm_campaign=yelp_api_v3&utm_medium=api_v3_business_search&utm_source=sBCogxx-5i49wpeuzo-8mQ",
        "review_count":2093,
        "categories":[
           {
              "alias":"parks",
              "title":"Parks"
           }
        ],
        "rating":5,
        "coordinates":{
           "latitude":40.782418740809,
           "longitude":-73.9656022837641
        },
        "transactions":[

        ],
        "location":{
           "address1":"14 E 60th St",
           "address2":"",
           "address3":"Central Park Conservancy",
           "city":"New York",
           "zip_code":"10022",
           "country":"US",
           "state":"NY",
           "display_address":[
              "14 E 60th St",
              "Central Park Conservancy",
              "New York, NY 10022"
           ]
        },
        "phone":"+12123106600",
        "display_phone":"(212) 310-6600",
        "distance":8893.835855571413
     },
     {
        "id":"jnEv25Y2DosTq2sNnvmC9g",
        "alias":"los-tacos-no-1-new-york",
        "name":"Los Tacos No.1",
        "image_url":"https://s3-media2.fl.yelpcdn.com/bphoto/FU44TYl3PzXsE06G4W5aog/o.jpg",
        "is_closed":false,
        "url":"https://www.yelp.com/biz/los-tacos-no-1-new-york?adjust_creative=sBCogxx-5i49wpeuzo-8mQ&utm_campaign=yelp_api_v3&utm_medium=api_v3_business_search&utm_source=sBCogxx-5i49wpeuzo-8mQ",
        "review_count":2331,
        "categories":[
           {
              "alias":"tacos",
              "title":"Tacos"
           }
        ],
        "rating":4.5,
        "coordinates":{
           "latitude":40.7425547,
           "longitude":-74.0060838
        },
        "transactions":[

        ],
        "price":"$",
        "location":{
           "address1":"75 9th Ave",
           "address2":"",
           "address3":"",
           "city":"New York",
           "zip_code":"10011",
           "country":"US",
           "state":"NY",
           "display_address":[
              "75 9th Ave",
              "New York, NY 10011"
           ]
        },
        "phone":"+12122560343",
        "display_phone":"(212) 256-0343",
        "distance":4244.358699250552
     },
     {
        "id":"WHRHK3S1mQc3PmhwsGRvbw",
        "alias":"bibble-and-sip-new-york-2",
        "name":"Bibble & Sip",
        "image_url":"https://s3-media3.fl.yelpcdn.com/bphoto/zCUvBD2KTMNEps7TAuuecQ/o.jpg",
        "is_closed":false,
        "url":"https://www.yelp.com/biz/bibble-and-sip-new-york-2?adjust_creative=sBCogxx-5i49wpeuzo-8mQ&utm_campaign=yelp_api_v3&utm_medium=api_v3_business_search&utm_source=sBCogxx-5i49wpeuzo-8mQ",
        "review_count":3705,
        "categories":[
           {
              "alias":"coffee",
              "title":"Coffee & Tea"
           },
           {
              "alias":"bakeries",
              "title":"Bakeries"
           }
        ],
        "rating":4.5,
        "coordinates":{
           "latitude":40.76282,
           "longitude":-73.98518
        },
        "transactions":[

        ],
        "price":"$",
        "location":{
           "address1":"253 W 51st St",
           "address2":"",
           "address3":"",
           "city":"New York",
           "zip_code":"10019",
           "country":"US",
           "state":"NY",
           "display_address":[
              "253 W 51st St",
              "New York, NY 10019"
           ]
        },
        "phone":"+16466495116",
        "display_phone":"(646) 649-5116",
        "distance":6433.363832566172
     },
     {
        "id":"UA2M9QFZghe-9th2KwLoWQ",
        "alias":"burger-and-lobster-new-york",
        "name":"Burger & Lobster",
        "image_url":"https://s3-media1.fl.yelpcdn.com/bphoto/LLteoVFm9lUAJI0thmMZiA/o.jpg",
        "is_closed":false,
        "url":"https://www.yelp.com/biz/burger-and-lobster-new-york?adjust_creative=sBCogxx-5i49wpeuzo-8mQ&utm_campaign=yelp_api_v3&utm_medium=api_v3_business_search&utm_source=sBCogxx-5i49wpeuzo-8mQ",
        "review_count":4450,
        "categories":[
           {
              "alias":"seafood",
              "title":"Seafood"
           },
           {
              "alias":"burgers",
              "title":"Burgers"
           },
           {
              "alias":"newamerican",
              "title":"American (New)"
           }
        ],
        "rating":4,
        "coordinates":{
           "latitude":40.74016,
           "longitude":-73.993372
        },
        "transactions":[
           "restaurant_reservation",
           "delivery",
           "pickup"
        ],
        "price":"$$",
        "location":{
           "address1":"39 W 19th St",
           "address2":"",
           "address3":"",
           "city":"New York",
           "zip_code":"10011",
           "country":"US",
           "state":"NY",
           "display_address":[
              "39 W 19th St",
              "New York, NY 10011"
           ]
        },
        "phone":"+16468337532",
        "display_phone":"(646) 833-7532",
        "distance":3860.923230585706
     },
     {
        "id":"veq1Bl1DW3UWMekZJUsG1Q",
        "alias":"gramercy-tavern-new-york",
        "name":"Gramercy Tavern",
        "image_url":"https://s3-media4.fl.yelpcdn.com/bphoto/mKMCanhddF9Hs6WOQ-VFyw/o.jpg",
        "is_closed":false,
        "url":"https://www.yelp.com/biz/gramercy-tavern-new-york?adjust_creative=sBCogxx-5i49wpeuzo-8mQ&utm_campaign=yelp_api_v3&utm_medium=api_v3_business_search&utm_source=sBCogxx-5i49wpeuzo-8mQ",
        "review_count":2540,
        "categories":[
           {
              "alias":"newamerican",
              "title":"American (New)"
           }
        ],
        "rating":4.5,
        "coordinates":{
           "latitude":40.738527,
           "longitude":-73.988417
        },
        "transactions":[

        ],
        "price":"$$$$",
        "location":{
           "address1":"42 E 20th St",
           "address2":"",
           "address3":"",
           "city":"New York",
           "zip_code":"10003",
           "country":"US",
           "state":"NY",
           "display_address":[
              "42 E 20th St",
              "New York, NY 10003"
           ]
        },
        "phone":"+12124770777",
        "display_phone":"(212) 477-0777",
        "distance":3711.7439058285554
     },
     {
        "id":"JION8hhg7q6zyayHYwhxIw",
        "alias":"the-high-line-new-york",
        "name":"The High Line",
        "image_url":"https://s3-media3.fl.yelpcdn.com/bphoto/A-WMM_ocFEi2Su4_UaZIow/o.jpg",
        "is_closed":false,
        "url":"https://www.yelp.com/biz/the-high-line-new-york?adjust_creative=sBCogxx-5i49wpeuzo-8mQ&utm_campaign=yelp_api_v3&utm_medium=api_v3_business_search&utm_source=sBCogxx-5i49wpeuzo-8mQ",
        "review_count":2148,
        "categories":[
           {
              "alias":"parks",
              "title":"Parks"
           },
           {
              "alias":"localflavor",
              "title":"Local Flavor"
           }
        ],
        "rating":4.5,
        "coordinates":{
           "latitude":40.7479831752801,
           "longitude":-74.0048906107511
        },
        "transactions":[

        ],
        "location":{
           "address1":"820 Washington St",
           "address2":"",
           "address3":"",
           "city":"New York",
           "zip_code":"10014",
           "country":"US",
           "state":"NY",
           "display_address":[
              "820 Washington St",
              "New York, NY 10014"
           ]
        },
        "phone":"+12122069922",
        "display_phone":"(212) 206-9922",
        "distance":4813.598883567381
     },
     {
        "id":"lWOkeS-wV4no8qqA9OwwEg",
        "alias":"doughnut-plant-new-york-4",
        "name":"Doughnut Plant",
        "image_url":"https://s3-media2.fl.yelpcdn.com/bphoto/7M6LUrA-Hq3yEmxWJ7yi5Q/o.jpg",
        "is_closed":false,
        "url":"https://www.yelp.com/biz/doughnut-plant-new-york-4?adjust_creative=sBCogxx-5i49wpeuzo-8mQ&utm_campaign=yelp_api_v3&utm_medium=api_v3_business_search&utm_source=sBCogxx-5i49wpeuzo-8mQ",
        "review_count":3037,
        "categories":[
           {
              "alias":"donuts",
              "title":"Donuts"
           },
           {
              "alias":"coffee",
              "title":"Coffee & Tea"
           }
        ],
        "rating":4.5,
        "coordinates":{
           "latitude":40.7163944930004,
           "longitude":-73.9886098620298
        },
        "transactions":[

        ],
        "price":"$$",
        "location":{
           "address1":"379 Grand St",
           "address2":"",
           "address3":"",
           "city":"New York",
           "zip_code":"10002",
           "country":"US",
           "state":"NY",
           "display_address":[
              "379 Grand St",
              "New York, NY 10002"
           ]
        },
        "phone":"+12125053700",
        "display_phone":"(212) 505-3700",
        "distance":1308.3879515578776
     },
     {
        "id":"FEVQpbOPOwAPNIgO7D3xxw",
        "alias":"shake-shack-new-york-2",
        "name":"Shake Shack",
        "image_url":"https://s3-media3.fl.yelpcdn.com/bphoto/J0UoRJKdaMl0EPdgxYIlKw/o.jpg",
        "is_closed":false,
        "url":"https://www.yelp.com/biz/shake-shack-new-york-2?adjust_creative=sBCogxx-5i49wpeuzo-8mQ&utm_campaign=yelp_api_v3&utm_medium=api_v3_business_search&utm_source=sBCogxx-5i49wpeuzo-8mQ",
        "review_count":5402,
        "categories":[
           {
              "alias":"burgers",
              "title":"Burgers"
           },
           {
              "alias":"foodstands",
              "title":"Food Stands"
           },
           {
              "alias":"icecream",
              "title":"Ice Cream & Frozen Yogurt"
           }
        ],
        "rating":4,
        "coordinates":{
           "latitude":40.7414000197233,
           "longitude":-73.98815019045
        },
        "transactions":[
           "delivery"
        ],
        "price":"$$",
        "location":{
           "address1":"Madison Square Park",
           "address2":"",
           "address3":"E 23rd St & Madison Ave",
           "city":"New York",
           "zip_code":"10010",
           "country":"US",
           "state":"NY",
           "display_address":[
              "Madison Square Park",
              "E 23rd St & Madison Ave",
              "New York, NY 10010"
           ]
        },
        "phone":"+12128896600",
        "display_phone":"(212) 889-6600",
        "distance":4031.402495127816
     },
     {
        "id":"4yPqqJDJOQX69gC66YUDkA",
        "alias":"peter-luger-brooklyn-2",
        "name":"Peter Luger",
        "image_url":"https://s3-media2.fl.yelpcdn.com/bphoto/DnReRUkXRtsmKycQEYl0pg/o.jpg",
        "is_closed":false,
        "url":"https://www.yelp.com/biz/peter-luger-brooklyn-2?adjust_creative=sBCogxx-5i49wpeuzo-8mQ&utm_campaign=yelp_api_v3&utm_medium=api_v3_business_search&utm_source=sBCogxx-5i49wpeuzo-8mQ",
        "review_count":4798,
        "categories":[
           {
              "alias":"steak",
              "title":"Steakhouses"
           }
        ],
        "rating":4,
        "coordinates":{
           "latitude":40.709945,
           "longitude":-73.962478
        },
        "transactions":[

        ],
        "price":"$$$$",
        "location":{
           "address1":"178 Broadway",
           "address2":"",
           "address3":"",
           "city":"Brooklyn",
           "zip_code":"11211",
           "country":"US",
           "state":"NY",
           "display_address":[
              "178 Broadway",
              "Brooklyn, NY 11211"
           ]
        },
        "phone":"+17183877400",
        "display_phone":"(718) 387-7400",
        "distance":2728.016921522817
     },
     {
        "id":"vRrVSB-LegwUwIxpkeRVtQ",
        "alias":"le-bernardin-new-york",
        "name":"Le Bernardin",
        "image_url":"https://s3-media2.fl.yelpcdn.com/bphoto/O2auTfVN7mp7qSMoKQ81hQ/o.jpg",
        "is_closed":false,
        "url":"https://www.yelp.com/biz/le-bernardin-new-york?adjust_creative=sBCogxx-5i49wpeuzo-8mQ&utm_campaign=yelp_api_v3&utm_medium=api_v3_business_search&utm_source=sBCogxx-5i49wpeuzo-8mQ",
        "review_count":2184,
        "categories":[
           {
              "alias":"french",
              "title":"French"
           },
           {
              "alias":"lounges",
              "title":"Lounges"
           }
        ],
        "rating":4.5,
        "coordinates":{
           "latitude":40.761557,
           "longitude":-73.981763
        },
        "transactions":[

        ],
        "price":"$$$$",
        "location":{
           "address1":"155 W 51st St",
           "address2":"",
           "address3":"The Equitable Bldg",
           "city":"New York",
           "zip_code":"10019",
           "country":"US",
           "state":"NY",
           "display_address":[
              "155 W 51st St",
              "The Equitable Bldg",
              "New York, NY 10019"
           ]
        },
        "phone":"+12125541515",
        "display_phone":"(212) 554-1515",
        "distance":6328.07179784047
     },
     {
        "id":"j1S3NUrkB3BVT49n_e76NQ",
        "alias":"best-bagel-and-coffee-new-york",
        "name":"Best Bagel & Coffee",
        "image_url":"https://s3-media2.fl.yelpcdn.com/bphoto/fZzpV8mvVVTd7uV19cZ7sg/o.jpg",
        "is_closed":false,
        "url":"https://www.yelp.com/biz/best-bagel-and-coffee-new-york?adjust_creative=sBCogxx-5i49wpeuzo-8mQ&utm_campaign=yelp_api_v3&utm_medium=api_v3_business_search&utm_source=sBCogxx-5i49wpeuzo-8mQ",
        "review_count":2374,
        "categories":[
           {
              "alias":"bagels",
              "title":"Bagels"
           },
           {
              "alias":"coffee",
              "title":"Coffee & Tea"
           },
           {
              "alias":"breakfast_brunch",
              "title":"Breakfast & Brunch"
           }
        ],
        "rating":4.5,
        "coordinates":{
           "latitude":40.7522683,
           "longitude":-73.9910861
        },
        "transactions":[

        ],
        "price":"$",
        "location":{
           "address1":"225 W 35th St",
           "address2":"",
           "address3":"",
           "city":"New York",
           "zip_code":"10001",
           "country":"US",
           "state":"NY",
           "display_address":[
              "225 W 35th St",
              "New York, NY 10001"
           ]
        },
        "phone":"+12125644409",
        "display_phone":"(212) 564-4409",
        "distance":5213.5315009761325
     },
     {
        "id":"nU4XBdvxDABXqZ6CnB8Dig",
        "alias":"clinton-street-baking-company-new-york-5",
        "name":"Clinton Street Baking Company",
        "image_url":"https://s3-media3.fl.yelpcdn.com/bphoto/1CTyUp3Fz_svoqmvi7hwAw/o.jpg",
        "is_closed":false,
        "url":"https://www.yelp.com/biz/clinton-street-baking-company-new-york-5?adjust_creative=sBCogxx-5i49wpeuzo-8mQ&utm_campaign=yelp_api_v3&utm_medium=api_v3_business_search&utm_source=sBCogxx-5i49wpeuzo-8mQ",
        "review_count":4268,
        "categories":[
           {
              "alias":"bakeries",
              "title":"Bakeries"
           },
           {
              "alias":"breakfast_brunch",
              "title":"Breakfast & Brunch"
           },
           {
              "alias":"tradamerican",
              "title":"American (Traditional)"
           }
        ],
        "rating":4,
        "coordinates":{
           "latitude":40.721128,
           "longitude":-73.983933
        },
        "transactions":[

        ],
        "price":"$$",
        "location":{
           "address1":"4 Clinton St",
           "address2":"",
           "address3":"",
           "city":"New York",
           "zip_code":"10002",
           "country":"US",
           "state":"NY",
           "display_address":[
              "4 Clinton St",
              "New York, NY 10002"
           ]
        },
        "phone":"+16466026263",
        "display_phone":"(646) 602-6263",
        "distance":1950.282829638887
     },
     {
        "id":"mvn2XFJfIPNAlvsy-arzkA",
        "alias":"brooklyn-bridge-brooklyn",
        "name":"Brooklyn Bridge",
        "image_url":"https://s3-media2.fl.yelpcdn.com/bphoto/i16PDm3rSzDaj8D47ggeXw/o.jpg",
        "is_closed":false,
        "url":"https://www.yelp.com/biz/brooklyn-bridge-brooklyn?adjust_creative=sBCogxx-5i49wpeuzo-8mQ&utm_campaign=yelp_api_v3&utm_medium=api_v3_business_search&utm_source=sBCogxx-5i49wpeuzo-8mQ",
        "review_count":1225,
        "categories":[
           {
              "alias":"landmarks",
              "title":"Landmarks & Historical Buildings"
           }
        ],
        "rating":4.5,
        "coordinates":{
           "latitude":40.7059677364821,
           "longitude":-73.9966657489186
        },
        "transactions":[

        ],
        "location":{
           "address1":"334 Furman St",
           "address2":null,
           "address3":"",
           "city":"Brooklyn",
           "zip_code":"11201",
           "country":"US",
           "state":"NY",
           "display_address":[
              "334 Furman St",
              "Brooklyn, NY 11201"
           ]
        },
        "phone":"+17187246434",
        "display_phone":"(718) 724-6434",
        "distance":208.2689719737892
     },
     {
        "id":"nI1UYDCYUTt23TpGxqnLKg",
        "alias":"buddakan-new-york",
        "name":"Buddakan",
        "image_url":"https://s3-media4.fl.yelpcdn.com/bphoto/Avw19VU35-FZLen3nl9gYw/o.jpg",
        "is_closed":false,
        "url":"https://www.yelp.com/biz/buddakan-new-york?adjust_creative=sBCogxx-5i49wpeuzo-8mQ&utm_campaign=yelp_api_v3&utm_medium=api_v3_business_search&utm_source=sBCogxx-5i49wpeuzo-8mQ",
        "review_count":3520,
        "categories":[
           {
              "alias":"chinese",
              "title":"Chinese"
           },
           {
              "alias":"bars",
              "title":"Bars"
           },
           {
              "alias":"asianfusion",
              "title":"Asian Fusion"
           }
        ],
        "rating":4,
        "coordinates":{
           "latitude":40.7422762672197,
           "longitude":-74.0048000961542
        },
        "transactions":[
           "delivery",
           "pickup"
        ],
        "price":"$$$",
        "location":{
           "address1":"75 9th Ave",
           "address2":null,
           "address3":"",
           "city":"New York",
           "zip_code":"10011",
           "country":"US",
           "state":"NY",
           "display_address":[
              "75 9th Ave",
              "New York, NY 10011"
           ]
        },
        "phone":"+12129896699",
        "display_phone":"(212) 989-6699",
        "distance":4190.079294335545
     },
     {
        "id":"UGECJrPSWy0n7PXykBBWAQ",
        "alias":"two-little-red-hens-new-york-4",
        "name":"Two Little Red Hens",
        "image_url":"https://s3-media3.fl.yelpcdn.com/bphoto/gF02Oh2PfE2OS7Nz3MqV4g/o.jpg",
        "is_closed":false,
        "url":"https://www.yelp.com/biz/two-little-red-hens-new-york-4?adjust_creative=sBCogxx-5i49wpeuzo-8mQ&utm_campaign=yelp_api_v3&utm_medium=api_v3_business_search&utm_source=sBCogxx-5i49wpeuzo-8mQ",
        "review_count":2260,
        "categories":[
           {
              "alias":"bakeries",
              "title":"Bakeries"
           },
           {
              "alias":"desserts",
              "title":"Desserts"
           },
           {
              "alias":"coffee",
              "title":"Coffee & Tea"
           }
        ],
        "rating":4.5,
        "coordinates":{
           "latitude":40.777528,
           "longitude":-73.9517869
        },
        "transactions":[

        ],
        "price":"$$",
        "location":{
           "address1":"1652 2nd Ave",
           "address2":null,
           "address3":"",
           "city":"New York",
           "zip_code":"10028",
           "country":"US",
           "state":"NY",
           "display_address":[
              "1652 2nd Ave",
              "New York, NY 10028"
           ]
        },
        "phone":"+12124520476",
        "display_phone":"(212) 452-0476",
        "distance":8778.875028640752
     },
     {
        "id":"a0IET3_yCFcO36OqGSsisg",
        "alias":"eataly-new-york",
        "name":"Eataly",
        "image_url":"https://s3-media2.fl.yelpcdn.com/bphoto/GOC-gTMsYsfxQUy-ZOUpdQ/o.jpg",
        "is_closed":false,
        "url":"https://www.yelp.com/biz/eataly-new-york?adjust_creative=sBCogxx-5i49wpeuzo-8mQ&utm_campaign=yelp_api_v3&utm_medium=api_v3_business_search&utm_source=sBCogxx-5i49wpeuzo-8mQ",
        "review_count":5015,
        "categories":[
           {
              "alias":"italian",
              "title":"Italian"
           },
           {
              "alias":"grocery",
              "title":"Grocery"
           },
           {
              "alias":"cafes",
              "title":"Cafes"
           }
        ],
        "rating":4,
        "coordinates":{
           "latitude":40.74195877796,
           "longitude":-73.989716662832
        },
        "transactions":[

        ],
        "price":"$$",
        "location":{
           "address1":"200 5th Ave",
           "address2":"",
           "address3":"",
           "city":"New York",
           "zip_code":"10010",
           "country":"US",
           "state":"NY",
           "display_address":[
              "200 5th Ave",
              "New York, NY 10010"
           ]
        },
        "phone":"+12122292560",
        "display_phone":"(212) 229-2560",
        "distance":4078.4333537925154
     },
     {
        "id":"jjJc_CrkB2HodEinB6cWww",
        "alias":"lovemama-new-york",
        "name":"LoveMama",
        "image_url":"https://s3-media1.fl.yelpcdn.com/bphoto/bLlFKTlVuLfmF-lIDGIjZA/o.jpg",
        "is_closed":false,
        "url":"https://www.yelp.com/biz/lovemama-new-york?adjust_creative=sBCogxx-5i49wpeuzo-8mQ&utm_campaign=yelp_api_v3&utm_medium=api_v3_business_search&utm_source=sBCogxx-5i49wpeuzo-8mQ",
        "review_count":3330,
        "categories":[
           {
              "alias":"thai",
              "title":"Thai"
           },
           {
              "alias":"malaysian",
              "title":"Malaysian"
           },
           {
              "alias":"vietnamese",
              "title":"Vietnamese"
           }
        ],
        "rating":4,
        "coordinates":{
           "latitude":40.7303859,
           "longitude":-73.9860613
        },
        "transactions":[
           "delivery",
           "pickup"
        ],
        "price":"$$",
        "location":{
           "address1":"174 2nd Ave",
           "address2":"",
           "address3":"",
           "city":"New York",
           "zip_code":"10003",
           "country":"US",
           "state":"NY",
           "display_address":[
              "174 2nd Ave",
              "New York, NY 10003"
           ]
        },
        "phone":"+12122545370",
        "display_phone":"(212) 254-5370",
        "distance":2858.7729410008346
     }
  ],
  "total":22800,
  "region":{
     "center":{
        "longitude":-73.99429321289062,
        "latitude":40.70544486444615
     }
  }
}